odoo/addons/l10n_br_crm/README.rst
odoo/addons/l10n_br_crm/__init__.py
odoo/addons/l10n_br_crm/__manifest__.py
odoo/addons/l10n_br_crm/i18n/es.po
odoo/addons/l10n_br_crm/i18n/l10n_br_crm.pot
odoo/addons/l10n_br_crm/i18n/pt_BR.po
odoo/addons/l10n_br_crm/models/__init__.py
odoo/addons/l10n_br_crm/models/crm_lead.py
odoo/addons/l10n_br_crm/readme/CONFIGURE.md
odoo/addons/l10n_br_crm/readme/CONTRIBUTORS.md
odoo/addons/l10n_br_crm/readme/DESCRIPTION.md
odoo/addons/l10n_br_crm/readme/INSTALL.md
odoo/addons/l10n_br_crm/readme/ROADMAP.md
odoo/addons/l10n_br_crm/readme/USAGE.md
odoo/addons/l10n_br_crm/static/description/icon.png
odoo/addons/l10n_br_crm/static/description/index.html
odoo/addons/l10n_br_crm/tests/__init__.py
odoo/addons/l10n_br_crm/tests/test_crm_lead.py
odoo/addons/l10n_br_crm/tests/test_crm_onchange.py
odoo/addons/l10n_br_crm/views/crm_lead_view.xml
odoo/addons/l10n_br_crm/views/crm_quick_create_opportunity_form.xml
odoo_addon_l10n_br_crm-18.0.1.1.0.2.dist-info/METADATA
odoo_addon_l10n_br_crm-18.0.1.1.0.2.dist-info/WHEEL
odoo_addon_l10n_br_crm-18.0.1.1.0.2.dist-info/top_level.txt
odoo_addon_l10n_br_crm-18.0.1.1.0.2.dist-info/RECORD
